pylayers_signal/__init__.py
pylayers_signal/bsignal.py
pylayers_signal/df.py
pylayers_signal/ed.py
pylayers_signal/plotutil.py
pylayers_signal/tests/test_bsignal.py
pylayers_signal-0.3.dist-info/LICENSE
pylayers_signal-0.3.dist-info/METADATA
pylayers_signal-0.3.dist-info/WHEEL
pylayers_signal-0.3.dist-info/top_level.txt
pylayers_signal-0.3.dist-info/RECORD
